trackmol/.DS_Store
trackmol/__init__.py
trackmol/skeleton.py
trackmol/__pycache__/__init__.cpython-311.pyc
trackmol/analysis/.DS_Store
trackmol/analysis/.gitkeep
trackmol/analysis/__init__.py
trackmol/analysis/donnees.py
trackmol/clustering/__init__.py
trackmol/clustering/clustering_utils.py
trackmol/computer_vision/.gitkeep
trackmol/computer_vision/__init__.py
trackmol/computer_vision/computer_vision_and__tracking.py
trackmol/computer_vision/computer_vision_and__tracking_groupby.py
trackmol/examples/.DS_Store
trackmol/examples/.gitkeep
trackmol/examples/Clustering.ipynb
trackmol/examples/.ipynb_checkpoints/Clustering-checkpoint.ipynb
trackmol/generation_walks/.DS_Store
trackmol/generation_walks/.gitkeep
trackmol/generation_walks/__init__.py
trackmol/generation_walks/statistical_generation.py
trackmol/gratin/.DS_Store
trackmol/gratin/__init__.py
trackmol/gratin/easy_predictions.py
trackmol/gratin/n2_+myoIb_1_trackedPar.csv
trackmol/gratin/standard.py
trackmol/gratin/__pycache__/__init__.cpython-311.pyc
trackmol/gratin/__pycache__/__init__.cpython-38.pyc
trackmol/gratin/__pycache__/standard.cpython-311.pyc
trackmol/gratin/data/.DS_Store
trackmol/gratin/data/__init__.py
trackmol/gratin/data/data.py
trackmol/gratin/data/data_tools.py
trackmol/gratin/data/datamodule.py
trackmol/gratin/data/dataset.py
trackmol/gratin/data/rep_dataset.py
trackmol/gratin/data/skeleton_data.py
trackmol/gratin/data/__pycache__/__init__.cpython-311.pyc
trackmol/gratin/data/__pycache__/data.cpython-311.pyc
trackmol/gratin/data/__pycache__/data_tools.cpython-311.pyc
trackmol/gratin/data/__pycache__/datamodule.cpython-311.pyc
trackmol/gratin/data/__pycache__/dataset.cpython-311.pyc
trackmol/gratin/data/__pycache__/skeleton_data.cpython-311.pyc
trackmol/gratin/layers/.DS_Store
trackmol/gratin/layers/InvNet.py
trackmol/gratin/layers/__init__.py
trackmol/gratin/layers/diverse.py
trackmol/gratin/layers/encoders.py
trackmol/gratin/layers/fBMGenerator.py
trackmol/gratin/layers/features_init.py
trackmol-1.0.0.dist-info/LICENSE.txt
trackmol-1.0.0.dist-info/METADATA
trackmol-1.0.0.dist-info/WHEEL
trackmol-1.0.0.dist-info/top_level.txt
trackmol-1.0.0.dist-info/RECORD
