Metadata-Version: 2.1
Name: trackmol
Version: 1.0.0
Summary: Add a short description here!
Home-page: https://github.com/pyscaffold/pyscaffold/
Author: Zakarie Aloui, Augustin Bouquillard, Noe Colomban, Jeanne Leclerc, Pierre Mazzucotelli, Ugo Wassermann
Author-email: zakarie.aloui@polytechnique.edu augustin.bouquillard.23@polytechnique.edu noe.colomban@polytechnique.edu jeanne.leclerc@polytechnique.edu pierre.mazzucotelli@gmail.com ugo.wassermann@polytechnique.edu
License: MIT
Project-URL: Documentation, https://pyscaffold.org/
Project-URL: Source, https://github.com/AugustinBouquillard/trackmol/
Platform: any
Classifier: Development Status :: 4 - Beta
Classifier: Programming Language :: Python
Requires-Dist: pandas
Requires-Dist: numpy
Requires-Dist: scipy
Requires-Dist: scikit-learn
Requires-Dist: matplotlib
Requires-Dist: fbm
Requires-Dist: tqdm
Requires-Dist: umap-learn[parametric_umap]>=0.5.2
Requires-Dist: torch
Provides-Extra: testing
Requires-Dist: setuptools; extra == "testing"
Requires-Dist: pytest; extra == "testing"
Requires-Dist: pytest-cov; extra == "testing"
